{"title":"Vibration-minimizing motion retargeting for robotic characters","doi":"10.1145/3306346.3323034","isbns":[],"altmetric_jid":"4f6fa4c83cf058f61000001d","issns":["0730-0301","1557-7368"],"journal":"ACM Transactions on Graphics","cohorts":[],"context":{"all":{"count":15549197,"mean":8.8980101187146,"rank":3814747,"pct":75,"higher_than":11666862},"journal":{"count":1964,"mean":6.2390779419256,"rank":636,"pct":67,"higher_than":1324},"similar_age_3m":{"count":261062,"mean":12.713678956259,"rank":79313,"pct":68,"higher_than":179800},"similar_age_journal_3m":{"count":23,"mean":8.2081818181818,"rank":8,"pct":65,"higher_than":15}},"authors":["Shayan Hoshyari","Hongyi Xu","Espen Knoop","Stelian Coros","Moritz Bächer"],"type":"article","handles":[],"altmetric_id":64324583,"schema":"1.5.4","is_oa":false,"publisher_subjects":[{"name":"Artificial Intelligence And Image Processing","scheme":"era"},{"name":"Information Systems","scheme":"era"}],"cited_by_feeds_count":1,"cited_by_posts_count":1,"cited_by_accounts_count":1,"last_updated":1564495310,"score":5.08,"history":{"1y":0,"6m":0,"3m":0,"1m":0,"1w":0,"6d":0,"5d":0,"4d":0,"3d":0,"2d":0,"1d":0,"at":5.08},"url":"http://dx.doi.org/10.1145/3306346.3323034","added_on":1564495562,"published_on":1562889600,"scopus_subjects":["Physical Sciences","Computer Science"],"readers":{"citeulike":"0","mendeley":"64","connotea":"0"},"readers_count":64,"images":{"small":"https://badges.altmetric.com/?size=64&score=6&types=bbbbbbbb","medium":"https://badges.altmetric.com/?size=100&score=6&types=bbbbbbbb","large":"https://badges.altmetric.com/?size=180&score=6&types=bbbbbbbb"},"details_url":"http://www.altmetric.com/details.php?citation_id=64324583"}