{
    "status": "ok",
    "message-type": "work",
    "message-version": "1.0.0",
    "message": {
        "indexed": {
            "date-parts": [
                [
                    2020,
                    4,
                    4
                ]
            ],
            "date-time": "2020-04-04T02:11:27Z",
            "timestamp": 1585966287114
        },
        "reference-count": 28,
        "publisher": "Association for Computing Machinery (ACM)",
        "issue": "4",
        "license": [
            {
                "URL": "http://www.acm.org/publications/policies/copyright_policy#Background",
                "start": {
                    "date-parts": [
                        [
                            2016,
                            7,
                            11
                        ]
                    ],
                    "date-time": "2016-07-11T00:00:00Z",
                    "timestamp": 1468195200000
                },
                "delay-in-days": 0,
                "content-version": "vor"
            }
        ],
        "funder": [
            {
                "DOI": "10.13039/501100001809",
                "name": "National Natural Science Foundation of China",
                "doi-asserted-by": "publisher",
                "award": [
                    "61272293"
                ]
            },
            {
                "DOI": "10.13039/501100002920",
                "name": "Research Grants Council, University Grants Committee",
                "doi-asserted-by": "publisher",
                "award": [
                    "CUHK 14200915"
                ]
            }
        ],
        "content-domain": {
            "domain": [],
            "crossmark-restriction": false
        },
        "short-container-title": [
            "ACM Trans. Graph."
        ],
        "published-print": {
            "date-parts": [
                [
                    2016,
                    7,
                    11
                ]
            ]
        },
        "DOI": "10.1145/2897824.2925872",
        "type": "journal-article",
        "created": {
            "date-parts": [
                [
                    2016,
                    7,
                    11
                ]
            ],
            "date-time": "2016-07-11T16:04:33Z",
            "timestamp": 1468253073000
        },
        "page": "1-10",
        "source": "Crossref",
        "is-referenced-by-count": 3,
        "title": [
            "Globally optimal toon tracking"
        ],
        "prefix": "10.1145",
        "volume": "35",
        "author": [
            {
                "given": "Haichao",
                "family": "Zhu",
                "sequence": "first",
                "affiliation": [
                    {
                        "name": "The Chinese University of Hong Kong"
                    }
                ]
            },
            {
                "given": "Xueting",
                "family": "Liu",
                "sequence": "additional",
                "affiliation": [
                    {
                        "name": "The Chinese University of Hong Kong"
                    }
                ]
            },
            {
                "given": "Tien-Tsin",
                "family": "Wong",
                "sequence": "additional",
                "affiliation": [
                    {
                        "name": "The Chinese University of Hong Kong"
                    }
                ]
            },
            {
                "given": "Pheng-Ann",
                "family": "Heng",
                "sequence": "additional",
                "affiliation": [
                    {
                        "name": "The Chinese University of Hong Kong"
                    }
                ]
            }
        ],
        "member": "320",
        "reference": [
            {
                "key": "e_1_2_2_1_1",
                "DOI": "10.1364/JOSAA.2.000284",
                "doi-asserted-by": "publisher"
            },
            {
                "key": "e_1_2_2_2_1",
                "DOI": "10.1007/s11263-010-0390-2",
                "doi-asserted-by": "publisher"
            },
            {
                "key": "e_1_2_2_3_1",
                "DOI": "10.1109/TPAMI.2011.21",
                "doi-asserted-by": "publisher"
            },
            {
                "key": "e_1_2_2_4_1",
                "DOI": "10.1145/566654.566595",
                "doi-asserted-by": "publisher"
            },
            {
                "key": "e_1_2_2_5_1",
                "DOI": "10.1109/CVPR.2013.241",
                "doi-asserted-by": "publisher"
            },
            {
                "key": "e_1_2_2_6_1",
                "author": "Horn B. K. P.",
                "volume-title": "Proceedings of International Society for Optics and Photonics Technical Symposium East, 319--331"
            },
            {
                "key": "e_1_2_2_7_1",
                "DOI": "10.1145/508530.508552",
                "doi-asserted-by": "publisher"
            },
            {
                "key": "e_1_2_2_8_1",
                "DOI": "10.1109/TPAMI.2007.41",
                "doi-asserted-by": "publisher"
            },
            {
                "key": "e_1_2_2_9_1",
                "DOI": "10.1145/2508363.2508396",
                "doi-asserted-by": "publisher"
            },
            {
                "key": "e_1_2_2_10_1",
                "author": "Lucas B. D.",
                "volume": "81",
                "volume-title": "Proceedings of International Joint Conference on Artificial Intelligence"
            },
            {
                "key": "e_1_2_2_11_1",
                "DOI": "10.1007/BF01782215",
                "doi-asserted-by": "publisher"
            },
            {
                "key": "e_1_2_2_12_1",
                "DOI": "10.1145/2024676.2024691",
                "doi-asserted-by": "publisher"
            },
            {
                "key": "e_1_2_2_13_1",
                "DOI": "10.1109/TPAMI.2014.2346202",
                "doi-asserted-by": "publisher"
            },
            {
                "key": "e_1_2_2_14_1",
                "author": "Pellegrini S.",
                "volume-title": "Proceedings of European Conference on Computer Vision, Springer, 452--465"
            },
            {
                "key": "e_1_2_2_15_1",
                "DOI": "10.1007/s00371-005-0307-1",
                "doi-asserted-by": "publisher"
            },
            {
                "key": "e_1_2_2_16_1",
                "DOI": "10.1109/TPAMI.2013.210",
                "doi-asserted-by": "publisher"
            },
            {
                "key": "e_1_2_2_17_1",
                "DOI": "10.1109/TPAMI.2013.230",
                "doi-asserted-by": "publisher"
            },
            {
                "key": "e_1_2_2_18_1",
                "DOI": "10.1016/j.neucom.2012.08.051",
                "doi-asserted-by": "publisher"
            },
            {
                "key": "e_1_2_2_19_1",
                "DOI": "10.1016/j.imavis.2005.05.010",
                "doi-asserted-by": "publisher"
            },
            {
                "key": "e_1_2_2_20_1",
                "DOI": "10.1145/1572614.1572619",
                "doi-asserted-by": "publisher"
            },
            {
                "key": "e_1_2_2_21_1",
                "DOI": "10.1145/2024676.2024689",
                "doi-asserted-by": "publisher"
            },
            {
                "key": "e_1_2_2_22_1",
                "first-page": "318",
                "article-title": "Autocorrelation: a principle for the evaluation of sensory information by the central nervous system",
                "volume": "303",
                "author": "Werner R.",
                "year": "1965",
                "journal-title": "Sensory Communication"
            },
            {
                "key": "e_1_2_2_23_1",
                "DOI": "10.1111/j.1467-8659.2009.01630.x",
                "doi-asserted-by": "publisher"
            },
            {
                "key": "e_1_2_2_24_1",
                "DOI": "10.1145/2816795.2818079",
                "doi-asserted-by": "publisher"
            },
            {
                "key": "e_1_2_2_25_1",
                "DOI": "10.1109/TPAMI.2011.236",
                "doi-asserted-by": "publisher"
            },
            {
                "key": "e_1_2_2_26_1",
                "DOI": "10.1287/mnsc.17.11.712",
                "doi-asserted-by": "publisher"
            },
            {
                "key": "e_1_2_2_27_1",
                "DOI": "10.1109/TVCG.2009.9",
                "doi-asserted-by": "publisher"
            },
            {
                "key": "e_1_2_2_28_1",
                "DOI": "10.1109/TVCG.2011.111",
                "doi-asserted-by": "publisher"
            }
        ],
        "container-title": [
            "ACM Transactions on Graphics"
        ],
        "original-title": [],
        "language": "en",
        "link": [
            {
                "URL": "http://dl.acm.org/ft_gateway.cfm?id=2925872&amp;ftid=1755866&amp;dwn=1",
                "content-type": "unspecified",
                "content-version": "vor",
                "intended-application": "similarity-checking"
            }
        ],
        "deposited": {
            "date-parts": [
                [
                    2020,
                    4,
                    4
                ]
            ],
            "date-time": "2020-04-04T01:35:59Z",
            "timestamp": 1585964159000
        },
        "score": 1.0,
        "subtitle": [],
        "short-title": [],
        "issued": {
            "date-parts": [
                [
                    2016,
                    7,
                    11
                ]
            ]
        },
        "references-count": 28,
        "journal-issue": {
            "published-print": {
                "date-parts": [
                    [
                        2016,
                        7,
                        11
                    ]
                ]
            },
            "issue": "4"
        },
        "alternative-id": [
            "10.1145/2897824.2925872"
        ],
        "URL": "http://dx.doi.org/10.1145/2897824.2925872",
        "relation": {
            "cites": []
        },
        "ISSN": [
            "0730-0301",
            "1557-7368"
        ],
        "issn-type": [
            {
                "value": "0730-0301",
                "type": "print"
            },
            {
                "value": "1557-7368",
                "type": "electronic"
            }
        ]
    }
}