{"title":"Predictive and generative neural networks for object functionality","doi":"10.1145/3197517.3201287","arxiv_id":"2006.15520","isbns":[],"altmetric_jid":"4f6fa4c83cf058f61000001d","issns":["0730-0301","1557-7368"],"journal":"ACM Transactions on Graphics","cohorts":{"pub":6},"context":{"all":{"count":16510152,"mean":9.2427562256643,"rank":8964987,"pct":45,"higher_than":7447426},"journal":{"count":1999,"mean":6.3295395395395,"rank":1777,"pct":11,"higher_than":222},"similar_age_3m":{"count":345430,"mean":12.483541792958,"rank":154959,"pct":54,"higher_than":187138},"similar_age_journal_3m":{"count":30,"mean":8.9059310344828,"rank":18,"pct":40,"higher_than":12}},"authors":["Ruizhen Hu","Zihao Yan","Jingwen Zhang","Oliver Van Kaick","Ariel Shamir","Hao Zhang","Hui Huang"],"type":"article","handles":[],"altmetric_id":52775839,"schema":"1.5.4","is_oa":false,"publisher_subjects":[{"name":"Artificial Intelligence And Image Processing","scheme":"era"},{"name":"Information Systems","scheme":"era"}],"cited_by_posts_count":10,"cited_by_tweeters_count":6,"cited_by_accounts_count":6,"last_updated":1593533481,"score":2.25,"history":{"1y":2.25,"6m":0,"3m":0,"1m":0,"1w":0,"6d":0,"5d":0,"4d":0,"3d":0,"2d":0,"1d":0,"at":2.25},"url":"http://dx.doi.org/10.1145/3197517.3201287","added_on":1545062575,"published_on":1533859200,"scopus_subjects":["Physical Sciences","Computer Science"],"readers":{"citeulike":"0","mendeley":"45","connotea":"0"},"readers_count":45,"images":{"small":"https://badges.altmetric.com/?size=64&score=3&types=tttttttt","medium":"https://badges.altmetric.com/?size=100&score=3&types=tttttttt","large":"https://badges.altmetric.com/?size=180&score=3&types=tttttttt"},"details_url":"http://www.altmetric.com/details.php?citation_id=52775839"}