{
    "status": "ok",
    "message-type": "work",
    "message-version": "1.0.0",
    "message": {
        "indexed": {
            "date-parts": [
                [
                    2020,
                    4,
                    4
                ]
            ],
            "date-time": "2020-04-04T02:11:26Z",
            "timestamp": 1585966286626
        },
        "reference-count": 51,
        "publisher": "Association for Computing Machinery (ACM)",
        "issue": "4",
        "license": [
            {
                "URL": "http://www.acm.org/publications/policies/copyright_policy#Background",
                "start": {
                    "date-parts": [
                        [
                            2016,
                            7,
                            11
                        ]
                    ],
                    "date-time": "2016-07-11T00:00:00Z",
                    "timestamp": 1468195200000
                },
                "delay-in-days": 0,
                "content-version": "vor"
            }
        ],
        "funder": [
            {
                "DOI": "10.13039/501100000287",
                "name": "Royal Academy of Engineering",
                "doi-asserted-by": "publisher",
                "award": []
            },
            {
                "DOI": "10.13039/501100001809",
                "name": "National Natural Science Foundation of China",
                "doi-asserted-by": "publisher",
                "award": [
                    "61120106007"
                ]
            },
            {
                "name": "Tsinghua University Initiative Scientific Research Program",
                "award": []
            },
            {
                "name": "the Royal Academy of Engineering and the Leverhulme Trust",
                "award": [
                    "LSRF1415/11/96"
                ]
            },
            {
                "name": "Research Grant of Beijing Higher Institution Engineering Research Center",
                "award": []
            }
        ],
        "content-domain": {
            "domain": [],
            "crossmark-restriction": false
        },
        "short-container-title": [
            "ACM Trans. Graph."
        ],
        "published-print": {
            "date-parts": [
                [
                    2016,
                    7,
                    11
                ]
            ]
        },
        "DOI": "10.1145/2897824.2925897",
        "type": "journal-article",
        "created": {
            "date-parts": [
                [
                    2016,
                    7,
                    11
                ]
            ],
            "date-time": "2016-07-11T16:04:33Z",
            "timestamp": 1468253073000
        },
        "page": "1-11",
        "source": "Crossref",
        "is-referenced-by-count": 20,
        "title": [
            "Multiphase SPH simulation for interactive fluids and solids"
        ],
        "prefix": "10.1145",
        "volume": "35",
        "author": [
            {
                "given": "Xiao",
                "family": "Yan",
                "sequence": "first",
                "affiliation": [
                    {
                        "name": "Tsinghua University"
                    }
                ]
            },
            {
                "given": "Yun-Tao",
                "family": "Jiang",
                "sequence": "additional",
                "affiliation": [
                    {
                        "name": "Tsinghua University"
                    }
                ]
            },
            {
                "given": "Chen-Feng",
                "family": "Li",
                "sequence": "additional",
                "affiliation": [
                    {
                        "name": "Swansea University"
                    }
                ]
            },
            {
                "given": "Ralph R.",
                "family": "Martin",
                "sequence": "additional",
                "affiliation": [
                    {
                        "name": "Cardiff University"
                    }
                ]
            },
            {
                "given": "Shi-Min",
                "family": "Hu",
                "sequence": "additional",
                "affiliation": [
                    {
                        "name": "Tsinghua University"
                    }
                ]
            }
        ],
        "member": "320",
        "reference": [
            {
                "key": "e_1_2_2_1_1",
                "DOI": "10.1145/2185520.2185558",
                "doi-asserted-by": "publisher"
            },
            {
                "key": "e_1_2_2_2_1",
                "DOI": "10.1002/cav.1499",
                "doi-asserted-by": "publisher"
            },
            {
                "key": "e_1_2_2_3_1",
                "DOI": "10.1145/2019406.2019410",
                "doi-asserted-by": "publisher"
            },
            {
                "key": "e_1_2_2_4_1",
                "DOI": "10.3208/sandf.36.13",
                "doi-asserted-by": "publisher"
            },
            {
                "key": "e_1_2_2_5_1",
                "author": "Becker M.",
                "volume-title": "Proceedings of the 2007 ACM SIGGRAPH/Eurographics Symposium on Computer Animation, 209--217"
            },
            {
                "key": "e_1_2_2_6_1",
                "DOI": "10.5555/2381692.2381696",
                "doi-asserted-by": "publisher"
            },
            {
                "key": "e_1_2_2_7_1",
                "DOI": "10.1145/1073368.1073379",
                "doi-asserted-by": "publisher"
            },
            {
                "key": "e_1_2_2_8_1",
                "DOI": "10.1145/2786784.2786796",
                "doi-asserted-by": "publisher"
            },
            {
                "key": "e_1_2_2_9_1",
                "DOI": "10.1002/nag.688",
                "doi-asserted-by": "publisher"
            },
            {
                "key": "e_1_2_2_10_1",
                "DOI": "10.1145/1599470.1599488",
                "doi-asserted-by": "publisher"
            },
            {
                "key": "e_1_2_2_11_1",
                "unstructured": "Gray J. Monaghan J. and Swift R. 2001. SPH elastic dynamics. Computer Methods in Applied Mechanics and Engineering 190 49C50 6641--6662.  Gray J. Monaghan J. and Swift R. 2001. SPH elastic dynamics. Computer Methods in Applied Mechanics and Engineering 190 49C50 6641--6662.",
                "DOI": "10.1016/S0045-7825(01)00254-7",
                "doi-asserted-by": "crossref"
            },
            {
                "key": "e_1_2_2_12_1",
                "DOI": "10.3208/sandf.36.1",
                "doi-asserted-by": "publisher"
            },
            {
                "key": "e_1_2_2_13_1",
                "unstructured": "Hill R. 1998. The Mathematical Theory of Plasticity. Oxford Clarendon Press.  Hill R. 1998. The Mathematical Theory of Plasticity . Oxford Clarendon Press."
            },
            {
                "key": "e_1_2_2_14_1",
                "unstructured": "Ihmsen M. Wahl A. and Teschner M. 2012. High-resolution simulation of granular material with sph. VRIPHYS 53--60.  Ihmsen M. Wahl A. and Teschner M. 2012. High-resolution simulation of granular material with sph. VRIPHYS 53--60."
            },
            {
                "key": "e_1_2_2_15_1",
                "DOI": "10.1109/TVCG.2013.105",
                "doi-asserted-by": "publisher"
            },
            {
                "key": "e_1_2_2_16_1",
                "unstructured": "Ihmsen M. Orthmann J. Solenthaler B. Kolb A. and Teschner M. 2014. SPH Fluids in Computer Graphics. Eurographics 2014 - State of the Art Reports.  Ihmsen M. Orthmann J. Solenthaler B. Kolb A. and Teschner M. 2014. SPH Fluids in Computer Graphics. Eurographics 2014 - State of the Art Reports."
            },
            {
                "key": "e_1_2_2_17_1",
                "DOI": "10.1145/2560795",
                "doi-asserted-by": "publisher"
            },
            {
                "key": "e_1_2_2_18_1",
                "DOI": "10.5555/2386366.2386387",
                "doi-asserted-by": "publisher"
            },
            {
                "key": "e_1_2_2_19_1",
                "DOI": "10.1002/nag.1610150806",
                "doi-asserted-by": "publisher"
            },
            {
                "key": "e_1_2_2_20_1",
                "DOI": "10.1111/j.1467-8659.2009.01360.x",
                "doi-asserted-by": "publisher"
            },
            {
                "key": "e_1_2_2_21_1",
                "DOI": "10.1145/1360612.1360648",
                "doi-asserted-by": "publisher"
            },
            {
                "key": "e_1_2_2_22_1",
                "unstructured": "Libersky L. and \n      \n      \n      Petschek A\n      \n  \n  . \n  1991\n  . Smooth particle hydrodynamics with strength of materials. In Advances in the Free-Lagrange Method Including Contributions on Adaptive Grid-ding and the Smooth Particle Hydrodynamics Method H. Trease M. Fritts and W. Crowley Eds. vol. \n  395\n   of \n  Lecture Notes in Physics\n  . \n  Springer Berlin Heidelberg 248--257.  Libersky L. and Petschek A. 1991. Smooth particle hydrodynamics with strength of materials. In Advances in the Free-Lagrange Method Including Contributions on Adaptive Grid-ding and the Smooth Particle Hydrodynamics Method H. Trease M. Fritts and W. Crowley Eds. vol. 395 of Lecture Notes in Physics . Springer Berlin Heidelberg 248--257.",
                "DOI": "10.1007/3-540-54960-9_58",
                "doi-asserted-by": "crossref"
            },
            {
                "key": "e_1_2_2_23_1",
                "DOI": "10.1145/2461912.2461984",
                "doi-asserted-by": "publisher"
            },
            {
                "key": "e_1_2_2_24_1",
                "DOI": "10.1145/2601097.2601152",
                "doi-asserted-by": "publisher"
            },
            {
                "key": "e_1_2_2_25_1",
                "unstructured": "Manninen M. Taivassalo V. and Kallio S. 1996. On the mixture model for multiphase flow. VTT Technical Research Centre of Finland 288.  Manninen M. Taivassalo V. and Kallio S. 1996. On the mixture model for multiphase flow. VTT Technical Research Centre of Finland 288."
            },
            {
                "key": "e_1_2_2_26_1",
                "DOI": "10.1145/1778765.1778776",
                "doi-asserted-by": "publisher"
            },
            {
                "key": "e_1_2_2_27_1",
                "DOI": "10.1146/annurev.aa.30.090192.002551",
                "doi-asserted-by": "publisher"
            },
            {
                "key": "e_1_2_2_28_1",
                "DOI": "10.1006/jcph.1997.5732",
                "doi-asserted-by": "publisher"
            },
            {
                "key": "e_1_2_2_29_1",
                "DOI": "10.1145/2010324.1964987",
                "doi-asserted-by": "publisher"
            },
            {
                "key": "e_1_2_2_30_1",
                "author": "M\u00fcller M.",
                "volume-title": "Proceedings of the 2003 ACM SIGGRAPH/Eurographics Symposium on Computer Animation, 154--159"
            },
            {
                "key": "e_1_2_2_31_1",
                "DOI": "10.1145/1028523.1028542",
                "doi-asserted-by": "publisher"
            },
            {
                "key": "e_1_2_2_32_1",
                "author": "M\u00fcller M.",
                "volume-title": "ACM SIGGRAPH 2005 Papers, 471--478"
            },
            {
                "key": "e_1_2_2_33_1",
                "DOI": "10.1145/1073368.1073402",
                "doi-asserted-by": "publisher"
            },
            {
                "key": "e_1_2_2_34_1",
                "unstructured": "Narain R. Golas A. and Lin M. C. 2010. Free-flowing granular materials with two-way solid coupling. ACM SIGGRAPH Asia 2010 Papers 173:1--173:10. 10.1145/1866158.1866195   Narain R. Golas A. and Lin M. C. 2010. Free-flowing granular materials with two-way solid coupling. ACM SIGGRAPH Asia 2010 Papers 173:1--173:10. 10.1145/1866158.1866195",
                "DOI": "10.1145/1882262.1866195",
                "doi-asserted-by": "crossref"
            },
            {
                "key": "e_1_2_2_35_1",
                "DOI": "10.1145/2766925",
                "doi-asserted-by": "publisher"
            },
            {
                "key": "e_1_2_2_36_1",
                "DOI": "10.1002/1097-0207(20000810)48:10<1445::AID-NME831>3.0.CO;2-9",
                "doi-asserted-by": "publisher"
            },
            {
                "key": "e_1_2_2_37_1",
                "DOI": "10.1145/2645703",
                "doi-asserted-by": "publisher"
            },
            {
                "key": "e_1_2_2_38_1",
                "DOI": "10.1016/0022-0396(87)90038-6",
                "doi-asserted-by": "publisher"
            },
            {
                "key": "e_1_2_2_39_1",
                "DOI": "10.1111/cgf.12467",
                "doi-asserted-by": "publisher"
            },
            {
                "key": "e_1_2_2_40_1",
                "author": "Solenthaler B.",
                "volume-title": "SCA '08"
            },
            {
                "key": "e_1_2_2_41_1",
                "DOI": "10.1145/1531326.1531346",
                "doi-asserted-by": "publisher"
            },
            {
                "key": "e_1_2_2_42_1",
                "DOI": "10.1002/cav.v18:1",
                "doi-asserted-by": "publisher"
            },
            {
                "key": "e_1_2_2_43_1",
                "DOI": "10.1145/2461912.2461948",
                "doi-asserted-by": "publisher"
            },
            {
                "key": "e_1_2_2_44_1",
                "DOI": "10.1145/2601097.2601176",
                "doi-asserted-by": "publisher"
            },
            {
                "key": "e_1_2_2_45_1",
                "unstructured": "Sulsky D. Chen Z. and Schreyer H. 1994. A particle method for history-dependent materials. Computer Methods in Applied Mechanics and Engineering 118 1C2 179--196.  Sulsky D. Chen Z. and Schreyer H. 1994. A particle method for history-dependent materials. Computer Methods in Applied Mechanics and Engineering 118 1C2 179--196.",
                "DOI": "10.1016/0045-7825(94)90112-0",
                "doi-asserted-by": "crossref"
            },
            {
                "key": "e_1_2_2_46_1",
                "DOI": "10.1006/jcph.1995.1010",
                "doi-asserted-by": "publisher"
            },
            {
                "key": "e_1_2_2_47_1",
                "DOI": "10.1111/cgf.12578",
                "doi-asserted-by": "publisher"
            },
            {
                "key": "e_1_2_2_48_1",
                "DOI": "10.1002/nag.1610181203",
                "doi-asserted-by": "publisher"
            },
            {
                "key": "e_1_2_2_49_1",
                "DOI": "10.1145/2816795.2818117",
                "doi-asserted-by": "publisher"
            },
            {
                "key": "e_1_2_2_50_1",
                "DOI": "10.1111/cgf.12229",
                "doi-asserted-by": "publisher"
            },
            {
                "key": "e_1_2_2_51_1",
                "DOI": "10.1145/1186822.1073298",
                "doi-asserted-by": "publisher"
            }
        ],
        "container-title": [
            "ACM Transactions on Graphics"
        ],
        "original-title": [],
        "language": "en",
        "link": [
            {
                "URL": "http://dl.acm.org/ft_gateway.cfm?id=2925897&amp;ftid=1755948&amp;dwn=1",
                "content-type": "unspecified",
                "content-version": "vor",
                "intended-application": "similarity-checking"
            }
        ],
        "deposited": {
            "date-parts": [
                [
                    2020,
                    4,
                    4
                ]
            ],
            "date-time": "2020-04-04T01:40:41Z",
            "timestamp": 1585964441000
        },
        "score": 1.0,
        "subtitle": [],
        "short-title": [],
        "issued": {
            "date-parts": [
                [
                    2016,
                    7,
                    11
                ]
            ]
        },
        "references-count": 51,
        "journal-issue": {
            "published-print": {
                "date-parts": [
                    [
                        2016,
                        7,
                        11
                    ]
                ]
            },
            "issue": "4"
        },
        "alternative-id": [
            "10.1145/2897824.2925897"
        ],
        "URL": "http://dx.doi.org/10.1145/2897824.2925897",
        "relation": {
            "cites": []
        },
        "ISSN": [
            "0730-0301",
            "1557-7368"
        ],
        "issn-type": [
            {
                "value": "0730-0301",
                "type": "print"
            },
            {
                "value": "1557-7368",
                "type": "electronic"
            }
        ]
    }
}